{
  "currentCount": 5,
  "data": [
    {
      "계약시작일": "2025-04-08",
      "계약종료일": "2025-04-08",
      "공고번호": 2025930009,
      "공급규모": 1,
      "공급위치": "대전광역시 서구 도산로 79",
      "공급위치우편번호": 35335,
      "당첨자발표일": "2025-03-31",
      "모집공고일": "2025-03-21",
      "모집공고홈페이지주소": "https://www.applyhome.co.kr/ai/aia/selectAPTRemndrLttotPblancDetailView.do?houseManageNo=2025930009&pblancNo=2025930009",
      "문의처": "1588-9798",
      "사업주체명": "도마 변동11재정비촉진구역 주택재개발정비사업조합",
      "일반공급접수시작일": "2025-03-26",
      "일반공급접수종료일": "2025-03-26",
      "입주예정월": "2025-04",
      "주택관리번호": 2025930009,
      "주택구분코드": 6,
      "주택구분코드명": "불법행위 재공급",
      "주택명": "대전 도마·변동 11구역 호반써밋 그랜드센트럴",
      "청약접수시작일": "2025-03-26",
      "청약접수종료일": "2025-03-26",
      "특별공급접수시작일": null,
      "특별공급접수종료일": null,
      "홈페이지주소": "http://www.hobansummit-dmbd.co.kr"
    },
    {
      "계약시작일": "2025-04-04",
      "계약종료일": "2025-04-04",
      "공고번호": 2025910052,
      "공급규모": 4,
      "공급위치": "경기도 파주시 운정3지구 A39블록",
      "공급위치우편번호": 10865,
      "당첨자발표일": "2025-03-28",
      "모집공고일": "2025-03-20",
      "모집공고홈페이지주소": "https://www.applyhome.co.kr/ai/aia/selectAPTRemndrLttotPblancDetailView.do?houseManageNo=2025910052&pblancNo=2025910052",
      "문의처": "1588-9798",
      "사업주체명": "티에스리빙 주식회사",
      "일반공급접수시작일": null,
      "일반공급접수종료일": null,
      "입주예정월": "2025-04",
      "주택관리번호": 2025910052,
      "주택구분코드": 4,
      "주택구분코드명": "무순위",
      "주택명": "파주 운정신도시 A39BL 호반써밋",
      "청약접수시작일": "2025-03-25",
      "청약접수종료일": "2025-03-25",
      "특별공급접수시작일": null,
      "특별공급접수종료일": null,
      "홈페이지주소": "http://hobansummit-uj.co.kr/a39/index.html#"
    },
    {
      "계약시작일": "2025-03-30",
      "계약종료일": "2025-03-30",
      "공고번호": 2025910049,
      "공급규모": 9,
      "공급위치": "경기도 시흥시 논곡동 378",
      "공급위치우편번호": 14984,
      "당첨자발표일": "2025-03-28",
      "모집공고일": "2025-03-20",
      "모집공고홈페이지주소": "https://www.applyhome.co.kr/ai/aia/selectAPTRemndrLttotPblancDetailView.do?houseManageNo=2025910049&pblancNo=2025910049",
      "문의처": "1600-3320",
      "사업주체명": "주식회사 미산투자개발",
      "일반공급접수시작일": null,
      "일반공급접수종료일": null,
      "입주예정월": "2025-04",
      "주택관리번호": 2025910049,
      "주택구분코드": 4,
      "주택구분코드명": "무순위",
      "주택명": "효성해링턴 플레이스 목감역(무순위 12차)",
      "청약접수시작일": "2025-03-25",
      "청약접수종료일": "2025-03-25",
      "특별공급접수시작일": null,
      "특별공급접수종료일": null,
      "홈페이지주소": "https://www.효성해링턴플레이스목감역.com"
    },
    {
      "계약시작일": "2025-04-08",
      "계약종료일": "2025-04-08",
      "공고번호": 2025930012,
      "공급규모": 4,
      "공급위치": "전라남도 무안군 일로읍 망월리 남악신도시 오룡지구 44BL",
      "공급위치우편번호": 58582,
      "당첨자발표일": "2025-03-28",
      "모집공고일": "2025-03-19",
      "모집공고홈페이지주소": "https://www.applyhome.co.kr/ai/aia/selectAPTRemndrLttotPblancDetailView.do?houseManageNo=2025930012&pblancNo=2025930012",
      "문의처": "061-282-8004",
      "사업주체명": "우미건설(주)",
      "일반공급접수시작일": "2025-03-25",
      "일반공급접수종료일": "2025-03-25",
      "입주예정월": "2025-07",
      "주택관리번호": 2025930012,
      "주택구분코드": 6,
      "주택구분코드명": "불법행위 재공급",
      "주택명": "무안 오룡지구 우미린 2차(44BL)",
      "청약접수시작일": "2025-03-24",
      "청약접수종료일": "2025-03-25",
      "특별공급접수시작일": "2025-03-24",
      "특별공급접수종료일": "2025-03-24",
      "홈페이지주소": "https://mor.lynn.co.kr/"
    },
    {
      "계약시작일": "2025-03-29",
      "계약종료일": "2025-03-29",
      "공고번호": 2025910048,
      "공급규모": 10,
      "공급위치": "서울특별시 강동구 성내동 15번지 일대",
      "공급위치우편번호": 5379,
      "당첨자발표일": "2025-03-28",
      "모집공고일": "2025-03-19",
      "모집공고홈페이지주소": "https://www.applyhome.co.kr/ai/aia/selectAPTRemndrLttotPblancDetailView.do?houseManageNo=2025910048&pblancNo=2025910048",
      "문의처": "1533-7677",
      "사업주체명": "주식회사 코람코자산신탁",
      "일반공급접수시작일": null,
      "일반공급접수종료일": null,
      "입주예정월": "2025-06",
      "주택관리번호": 2025910048,
      "주택구분코드": 4,
      "주택구분코드명": "무순위",
      "주택명": "그란츠 리버파크(2차)",
      "청약접수시작일": "2025-03-24",
      "청약접수종료일": "2025-03-25",
      "특별공급접수시작일": null,
      "특별공급접수종료일": null,
      "홈페이지주소": "https://www.glanzlife.co.kr"
    }
  ],
  "matchCount": 1170,
  "page": 1,
  "perPage": 5,
  "totalCount": 1170
}